sqlalchemy_tools/__init__.py
sqlalchemy_tools/database.py
sqlalchemy_tools/forms.py
sqlalchemy_tools/mixins.py
sqlalchemy_tools/validator.py
sqlalchemy_tools/base/__init__.py
sqlalchemy_tools/base/model.py
sqlalchemy_tools/base/query.py
sqlalchemy_tools/base/repr.py
sqlalchemy_tools/migration/__init__.py
sqlalchemy_tools/migration/manager/__init__.py
sqlalchemy_tools/migration/manager/cli.py
sqlalchemy_tools/migration/templates/default/README
sqlalchemy_tools/migration/templates/default/alembic.ini.mako
sqlalchemy_tools/migration/templates/default/env.py
sqlalchemy_tools/migration/templates/default/script.py.mako
sqlalchemy_tools/pagination/__init__.py
sqlalchemy_tools/pagination/paginator.py
sqlalchemy_tools/pagination/test_paginator.py
SqlAlchemy_Tools-0.2.0.dist-info/LICENSE
SqlAlchemy_Tools-0.2.0.dist-info/METADATA
SqlAlchemy_Tools-0.2.0.dist-info/WHEEL
SqlAlchemy_Tools-0.2.0.dist-info/top_level.txt
SqlAlchemy_Tools-0.2.0.dist-info/RECORD
