Metadata-Version: 2.1
Name: SqlAlchemy-Tools
Version: 0.2.0
Summary: SqlAlchemyTools provides similar functionality to Flask-SqlAlchemy & Flask-Migrate without being dependant on Flask.
Home-page: https://github.com/AndyEveritt/SqlAlchemyTools
Author: Andy Everitt
Author-email: andreweveritt@e3d-online.com
Classifier: License :: OSI Approved :: MIT License
Classifier: Programming Language :: Python :: 3
Classifier: Operating System :: OS Independent
License-File: LICENSE
Requires-Dist: alembic (>=1.5.4)
Requires-Dist: arrow (>=0.17.0)
Requires-Dist: flask-wtf (>=0.14.3)
Requires-Dist: flask-validator (>=1.4.2)
Requires-Dist: inflection (>=0.5.1)
Requires-Dist: graphviz (>=0.16)
Requires-Dist: manage.py (>=0.2.10)
Requires-Dist: pandas (>=1.2.2)
Requires-Dist: pymysql (>=1.0.2)
Requires-Dist: pg8000 (>=1.17.0)
Requires-Dist: sadisplay (>=0.4.9)
Requires-Dist: sqlalchemy (<=1.4.48,>=1.3.23)
Requires-Dist: sqlalchemy-mixins (<=1.5.3,>=1.2.1)
Requires-Dist: sqlalchemy-repr (>=0.0.2)
Requires-Dist: wtforms-alchemy (>=0.17.0)
